terminal_parrot/__init__.py
terminal_parrot/main.py
terminal_parrot/animations/parrot.animation
terminal_parrot-0.1.0.dist-info/licenses/LICENSE
terminal_parrot-0.1.0.dist-info/METADATA
terminal_parrot-0.1.0.dist-info/WHEEL
terminal_parrot-0.1.0.dist-info/entry_points.txt
terminal_parrot-0.1.0.dist-info/top_level.txt
terminal_parrot-0.1.0.dist-info/RECORD
