Metadata-Version: 2.4
Name: terminal-parrot
Version: 0.1.0
Summary: Animated party parrot for your terminal 🦜
Author-email: Dharsini Sri <purpleunalome@gmail.com>
License: MIT
Requires-Python: >=3.7
License-File: LICENSE
Dynamic: license-file
